pibybit/__init__.py
pibybit/cli.py
pibybit/log.py
pibybit/piBybit.py
pibybit/utils.py
pibybit-0.1.0.dist-info/AUTHORS.rst
pibybit-0.1.0.dist-info/LICENSE
pibybit-0.1.0.dist-info/METADATA
pibybit-0.1.0.dist-info/WHEEL
pibybit-0.1.0.dist-info/entry_points.txt
pibybit-0.1.0.dist-info/top_level.txt
pibybit-0.1.0.dist-info/RECORD
