Metadata-Version: 2.1
Name: pibybit
Version: 0.1.0
Summary: Bybit package for PiAsset
Home-page: https://github.com/saaltfiish/pibybit
Author: Jiazhen Hu
Author-email: hujiazhen@piasset.net
License: MIT license
Keywords: pibybit
Platform: UNKNOWN
Classifier: Development Status :: 2 - Pre-Alpha
Classifier: Intended Audience :: Developers
Classifier: License :: OSI Approved :: MIT License
Classifier: Natural Language :: English
Classifier: Programming Language :: Python :: 3
Classifier: Programming Language :: Python :: 3.6
Classifier: Programming Language :: Python :: 3.7
Classifier: Programming Language :: Python :: 3.8
Requires-Python: >=3.6
License-File: LICENSE
License-File: AUTHORS.rst
